inference_interface.py
inference_interface-0.0.3.dist-info/LICENSE
inference_interface-0.0.3.dist-info/METADATA
inference_interface-0.0.3.dist-info/WHEEL
inference_interface-0.0.3.dist-info/top_level.txt
inference_interface-0.0.3.dist-info/RECORD
