Metadata-Version: 2.1
Name: inference-interface
Version: 0.0.3
Summary: Functions to read, convert and handle toyMC simulations, fit results and templates used by the XENONnT inference codes
Home-page: https://github.com/XENONnT/inference_interface
Author: XENONnT collaboration
Author-email: knut.dundas.moraa@columbia.edu
License: UNKNOWN
Platform: UNKNOWN
Classifier: Development Status :: 4 - Beta
Classifier: License :: OSI Approved :: BSD License
Classifier: Natural Language :: English
Classifier: Programming Language :: Python :: 3.8
Classifier: Programming Language :: Python :: 3.9
Classifier: Intended Audience :: Science/Research
Classifier: Programming Language :: Python :: Implementation :: CPython
Classifier: Topic :: Scientific/Engineering :: Physics
Requires-Python: >=3.8
Requires-Dist: h5py
Requires-Dist: multihist
Requires-Dist: numpy
